patch_all_collective_primi.py
run_daemon.py
work_monitor.py
group_cc_hook/__init__.py
group_cc_hook/config.py
group_cc_hook/patch_all_collective_primi.py
group_cc_hook/run_daemon.py
group_cc_hook/work_monitor.py
group_cc_hook-0.1.2.dist-info/LICENSE
group_cc_hook-0.1.2.dist-info/METADATA
group_cc_hook-0.1.2.dist-info/WHEEL
group_cc_hook-0.1.2.dist-info/top_level.txt
group_cc_hook-0.1.2.dist-info/RECORD
