Metadata-Version: 2.1
Name: group-cc-hook
Version: 0.1.2
Summary: A hook for torch.distributed ProcessGroup primitives with timeout detection
Home-page: https://github.com/yangrudan/group_cc_hook
Author: Yang Rudan
Keywords: pytorch distributed monitoring timeout hook nccl
Classifier: Development Status :: 3 - Alpha
Classifier: Intended Audience :: Developers
Classifier: Intended Audience :: Science/Research
Classifier: Topic :: Scientific/Engineering :: Artificial Intelligence
Classifier: Topic :: System :: Monitoring
Classifier: Programming Language :: Python :: 3
Classifier: Programming Language :: Python :: 3.7
Classifier: Programming Language :: Python :: 3.8
Classifier: Programming Language :: Python :: 3.9
Classifier: Programming Language :: Python :: 3.10
Classifier: Programming Language :: Python :: 3.11
Classifier: Programming Language :: Python :: Implementation :: CPython
Classifier: Operating System :: POSIX :: Linux
Requires-Python: >=3.7,<3.13
License-File: LICENSE
Requires-Dist: torch (<3.0.0,>=1.8.0)
